wyoming_satellite/__init__.py
wyoming_satellite/__main__.py
wyoming_satellite/example_event_client.py
wyoming_satellite/satellite.py
wyoming_satellite/settings.py
wyoming_satellite/utils.py
wyoming_satellite/vad.py
wyoming_satellite/webrtc.py
wyoming_satellite-1.0.0.dist-info/LICENSE.md
wyoming_satellite-1.0.0.dist-info/METADATA
wyoming_satellite-1.0.0.dist-info/WHEEL
wyoming_satellite-1.0.0.dist-info/entry_points.txt
wyoming_satellite-1.0.0.dist-info/top_level.txt
wyoming_satellite-1.0.0.dist-info/RECORD
